cain/__info__.py
cain/__init__.py
cain/__main__.py
cain/cain.py
cain/errors.py
cain/model.py
cain/types/__init__.py
cain/types/arrays.py
cain/types/binary.py
cain/types/booleans.py
cain/types/characters.py
cain/types/enums.py
cain/types/nonetype.py
cain/types/numbers.py
cain/types/objects.py
cain/types/optionals.py
cain/types/ranges.py
cain/types/sets.py
cain/types/strings.py
cain/types/tuples.py
cain/types/types.py
cain/types/unions.py
cain-1.1.1.dist-info/LICENSE
cain-1.1.1.dist-info/METADATA
cain-1.1.1.dist-info/WHEEL
cain-1.1.1.dist-info/entry_points.txt
cain-1.1.1.dist-info/RECORD
