Metadata-Version: 2.1
Name: cain
Version: 1.1.1
Summary: A small yet powerful data format ✨
Home-page: https://github.com/Animenosekai/cain
License: MIT
Keywords: animenosekai,cain,data,format
Author: Animenosekai
Author-email: animenosekai.mail@gmail.com
Maintainer: Animenosekai
Maintainer-email: animenosekai.mail@gmail.com
Requires-Python: >=3.9,<4.0
Classifier: Development Status :: 4 - Beta
Classifier: Environment :: Console
Classifier: Intended Audience :: Developers
Classifier: License :: OSI Approved :: MIT License
Classifier: Operating System :: OS Independent
Classifier: Programming Language :: Python
Classifier: Programming Language :: Python :: 3
Classifier: Programming Language :: Python :: 3.9
Classifier: Programming Language :: Python :: 3.10
Classifier: Programming Language :: Python :: 3.11
Classifier: Topic :: File Formats
Classifier: Topic :: System :: Archiving
Classifier: Typing :: Typed
Requires-Dist: typing_extensions (>=4.7,<5.0)
Project-URL: Documentation, https://github.com/Animenosekai/cain/blob/main/README.md
Project-URL: Issue Tracker, https://github.com/Animenosekai/cain/issues
Project-URL: Repository, https://github.com/Animenosekai/cain
